structsolve/__init__.py
structsolve/analysis.py
structsolve/arc_length_crisfield.py
structsolve/arc_length_riks.py
structsolve/freq.py
structsolve/linear_buckling.py
structsolve/logger.py
structsolve/newton_raphson.py
structsolve/sparseutils.py
structsolve/static.py
structsolve/version.py
structsolve-0.2.2.data/data/LICENSE
structsolve-0.2.2.data/data/README.md
structsolve-0.2.2.data/data/version.py
structsolve-0.2.2.dist-info/METADATA
structsolve-0.2.2.dist-info/RECORD
structsolve-0.2.2.dist-info/WHEEL
structsolve-0.2.2.dist-info/top_level.txt
