Metadata-Version: 1.1
Name: structsolve
Version: 0.2.2
Summary: Structural analysis solvers
Home-page: https://github.com/compmech/structsolve
Author: Saullo G. P. Castro
Author-email: castrosaullo@gmail.com
License: 3-Clause BSD
Keywords: structural analysis stress vibration linear buckling newton raphson arc length
Platform: UNKNOWN
Classifier: Development Status :: 3 - Alpha
Classifier: Intended Audience :: Science/Research
Classifier: Intended Audience :: Developers
Classifier: Intended Audience :: Education
Classifier: Topic :: Scientific/Engineering :: Mathematics
Classifier: License :: OSI Approved :: BSD License
Classifier: Operating System :: Microsoft :: Windows
Classifier: Programming Language :: Python :: 2.7
Classifier: Programming Language :: Python :: 3.5
Classifier: Programming Language :: Python :: 3.6
Classifier: Operating System :: Unix
